{"d9d39bcd-f7d9-4005-b40c-fd38b1806009":{"status":"03-act","level":1,"tags":null,"actual_hours":"0.10","weight":5,"description":"complete secured instance in the web:\n - OAuth2 , authorization and authentication \n - full CRUD ui for issues,projects,problems \n - history data management\n - time tracking biz features","type":"ysg","guid":"d9d39bcd-f7d9-4005-b40c-fd38b1806009","category":"issue-tracker","planned_hours":"900.00","start_time":"2019-01-01 00:00:00","id":1806241428,"stop_time":"2019-06-30 00:00:00","update_time":"2018-08-06 18:23:47","rows_count":1,"prio":5,"owner":"milestone","name":"complete secured instance in the web","seq":null}}