{
   "multi_lines_comment" : "to indicate new line use \\n, to indicate 3 spaces \\t",
   "env" : {
      "ENV_TYPE" : "prd",
      "aws" : {
         "availability_zone" : "eu-west-1c",
         "bucket" : "qto.fi",
         "AWS_ACCESS_KEY_ID" : "memghXl8Mrme",
         "pem_key_fpath" : "~/.ssh/id_rsa.aws-ec2.qto.prd",
         "ssh_key_pair_file" : "~/.ssh/key-pair-qto-amzn.pem",
         "pem_key_fpath_pub" : "~/.ssh/id_rsa.aws-ec2.qto.prd.pub",
         "AdminEmail" : "yordan.georgiev@gmail.com",
         "AWS_SECRET_ACCESS_KEY" : "kgI6kw8PbUxP",
         "AWS_DEFAULT_REGION" : "eu-west-1"
      },
      "redis" : {
         "server" : "127.0.0.1",
         "port" : "6379"
      },
      "app" : {
         "port" : "8080",
         "https_port" : "443",
         "mojo_morbo_port" : "3003",
         "postgres_db_name" : "prd_qto",
         "mojo_hypnotoad_port" : "8080",
         "ws_protocol" : "wss",
         "ht_protocol" : "http",
         "web_host" : "host-name",
         "num_of_workers" : "5",
         "nginx_port" : "80"
      },
      "git" : {
         "private_key_file" : "~/.ssh/id_rsa.ysg",
         "git_clone_url" : "git@github.com:YordanGeorgiev/qto.git"
      },
      "log" : {
         "PrintWarningMsgs" : 1,
         "PrintConsoleMsgs" : 1,
         "LogTimeToTextSeparator" : ":::",
         "PrintTraceMsgs" : 0,
         "PrintDebugMsgs" : 0,
         "PrintErrorMsgs" : 1,
         "LogFile" : "$LogDir/$ProductName.%YYYY%.%MM%.%DD%.log",
         "LogDir" : "$ProductInstanceDir/dat/log",
         "PrintInfoMsgs" : 1,
         "TimeFormat" : "YYYY-MM-DD hh:mm:ss",
         "LogToFile" : 1
      },
      "db" : {
         "postgres_db_useradmin_pw" : "SGg1mPhqHmD4",
         "postgres_db_host" : "127.0.0.1",
         "postgres_db_name" : "prd_qto",
         "postgres_db_useradmin" : "usrprdqtoadmin",
         "postgres_db_port" : "15432",
         "postgres_os_usr_pw" : "yt88RzegSMNs",
         "postgres_db_user" : "usrprdqtoapp",
         "project_databases" : "prd_csitea , prd_ysg",
         "AdminEmail" : "3ETMKpCRwG4W",
         "postgres_usr_pw" : "KOs60gtuQFj2",
         "app_user_pwd" : "KuN4p1BBMzIS",
         "postgres_db_user_pw" : "fwnfrXlCMPyL",
         "root_pwd" : "c7RN8xzWpW9h"
      },
      "ssh" : {
         "ssh_user" : "ubuntu",
         "ssh_server" : "qto.fi",
         "launch_dir" : "/home/ubuntu/dat/tmp"
      }
   }
}
