{
   "multi_lines_comment" : "to indicate new line use \\n, to indicate 3 spaces \\t",
   "env" : {
      "log" : {
         "PrintTraceMsgs" : 1,
         "LogDir" : "$ProductInstanceDir/dat/log",
         "PrintInfoMsgs" : 1,
         "PrintConsoleMsgs" : 1,
         "PrintWarningMsgs" : 1,
         "PrintErrorMsgs" : 1,
         "LogToFile" : 1,
         "PrintDebugMsgs" : 1,
         "LogTimeToTextSeparator" : ":::",
         "TimeFormat" : "YYYY-MM-DD hh:mm:ss",
         "LogFile" : "$LogDir/$ProductName.%YYYY%.%MM%.%DD%.log"
      },
      "aws" : {
         "ssh_key_pair_file" : "~/.ssh/key-pair-qto-amzn.pem",
         "AWS_DEFAULT_REGION" : "eu-west-1",
         "AWS_ACCESS_KEY_ID" : "NzRuurjirY8s",
         "key_name" : "id_rsa.ysg.pub",
         "public_key_path" : "/home/ysg/.ssh/id_rsa.ysg.pub",
         "public_key_path_comment" : "this one ^^^ has to be absolute file path",
         "bucket" : "qto.fi",
         "availability_zone" : "eu-west-1c",
         "AWS_SECRET_ACCESS_KEY" : "YOfYlfxpCNwp"
      },
      "git" : {
         "git_clone_url" : "git@github.com:YordanGeorgiev/qto.git",
         "private_key_file" : "~/.ssh/id_rsa.ysg"
      },
      "app" : {
         "port" : "8080",
         "nginx_port" : "80",
         "web_host" : "qto.fi",
         "ht_protocol" : "https",
         "ws_protocol" : "wss",
         "postgres_db_name" : "prd_qto",
         "mojo_morbo_port" : "3003",
         "https_port" : "443",
         "num_of_workers" : "5",
         "mojo_hypnotoad_port" : "8080"
      },
      "ENV_TYPE" : "tst",
      "db" : {
         "postgres_db_useradmin" : "usrprdqtoadmin",
         "root_pwd" : "rxLu6aw6Z4CS",
         "postgres_db_name" : "prd_qto",
         "postgres_db_user" : "usrprdqtoapp",
         "postgres_db_port" : "15432",
         "postgres_db_useradmin_pw" : "DJA8N3OizSyr",
         "postgres_usr_pw" : "Rq3rBBNuEsci",
         "postgres_os_usr_pw" : "EwwRxX0HgovU",
         "app_user_pwd" : "wOxwFgv75bG0",
         "postgres_db_host" : "127.0.0.1",
         "postgres_db_user_pw" : "UhdoFz81LqqG"
      },
      "ssh" : {
         "launch_dir" : "/home/ubuntu/dat/tmp",
         "ssh_user" : "ubuntu",
         "ssh_key_pair_file" : "~/.ssh/key-pair-qto-amzn.pem",
         "ssh_server" : "qto.fi"
      },
      "AdminEmail" : "wZZiZWfm1F34"
   }
}
