{
   "multi_lines_comment" : "to indicate new line use \\n, to indicate 3 spaces \\t",
   "env" : {
      "ssh" : {
         "ssh_user" : "ubuntu",
         "ssh_server" : "tst.qto.fi",
         "ssh_key_pair_file" : "~/.ssh/key-pair-qto-amzn.pem",
         "launch_dir" : "/home/ubuntu/dat/tmp"
      },
      "ENV_TYPE" : "tst",
      "log" : {
         "PrintErrorMsgs" : 1,
         "LogTimeToTextSeparator" : ":::",
         "PrintConsoleMsgs" : 1,
         "LogDir" : "$ProductInstanceDir/dat/log",
         "PrintTraceMsgs" : 1,
         "LogToFile" : 1,
         "PrintInfoMsgs" : 1,
         "LogFile" : "$LogDir/$ProductName.%YYYY%.%MM%.%DD%.log",
         "TimeFormat" : "YYYY-MM-DD hh:mm:ss",
         "PrintDebugMsgs" : 1,
         "PrintWarningMsgs" : 1
      },
      "app" : {
         "nginx_port" : "82",
         "port" : "8082",
         "web_host" : "dev.qto.fi",
         "mojo_morbo_port" : "3002",
         "postgres_db_name" : "tst_qto",
         "ht_protocol" : "http",
         "ws_protocol" : "ws",
         "num_of_workers" : "5",
         "mojo_hypnotoad_port" : "8082",
         "https_port" : "442"
      },
      "aws" : {
         "AWS_SECRET_ACCESS_KEY" : "hMA3jkfpDUWn",
         "key_name" : "id_rsa.ysg.pub",
         "AWS_ACCESS_KEY_ID" : "3WmDuWpUUBre",
         "AWS_DEFAULT_REGION" : "eu-west-1",
         "public_key_path_comment" : "this one ^^^ has to be absolute file path",
         "availability_zone" : "eu-west-1c",
         "public_key_path" : "/home/ysg/.ssh/id_rsa.ysg.pub",
         "ssh_key_pair_file" : "~/.ssh/key-pair-qto-amzn.pem",
         "bucket" : "qto.fi"
      },
      "db" : {
         "app_user_pwd" : "I74RCSwvDlgB",
         "postgres_db_useradmin_pw" : "Q6b6kC0PtHhV",
         "root_pwd" : "c7RN8xzWpW9h",
         "postgres_db_useradmin" : "usrtstqtoadmin",
         "postgres_db_user_pw" : "iJVBBImtsqtX",
         "postgres_db_host" : "127.0.0.1",
         "AdminEmail" : "0O7p7s92TWrC",
         "postgres_db_name" : "tst_qto",
         "postgres_db_user" : "usrtstqtoapp",
         "postgres_os_usr_pw" : "TsqZK7bkhTJe",
         "postgres_db_port" : "15432",
         "postgres_usr_pw" : "8Cltfrb5B4A5"
      },
      "git" : {
         "private_key_file" : "~/.ssh/id_rsa.ysg",
         "git_clone_url" : "git@github.com:YordanGeorgiev/qto.git"
      }
   }
}
