{
   "multi_lines_comment" : "to indicate new line use \\n, to indicate 3 spaces \\t",
   "env" : {
      "AdminEmail" : "k5SdTNo3K7EB",
      "log" : {
         "PrintErrorMsgs" : 1,
         "LogTimeToTextSeparator" : ":::",
         "LogFile" : "$LogDir/$ProductName.%YYYY%.%MM%.%DD%.log",
         "PrintInfoMsgs" : 1,
         "PrintWarningMsgs" : 1,
         "PrintTraceMsgs" : 1,
         "PrintConsoleMsgs" : 1,
         "TimeFormat" : "YYYY-MM-DD hh:mm:ss",
         "LogDir" : "$ProductInstanceDir/dat/log",
         "PrintDebugMsgs" : 1,
         "LogToFile" : 1
      },
      "app" : {
         "port" : "8080",
         "mojo_daemon_port" : "441",
         "mojo_morbo_port" : "3001",
         "ht_protocol" : "http",
         "mojo_hypnotoad_port" : "8081",
         "ws_protocol" : "ws",
         "postgres_db_name" : "dev_qto",
         "web_host" : "host-name"
      },
      "ssh" : {
         "ssh_user" : "ubuntu",
         "ssh_key_pair_file" : "~/.ssh/key-pair-qto-amzn.pem",
         "launch_dir" : "/home/ubuntu/dat/tmp",
         "ssh_server" : "host-name"
      },
      "ENV_TYPE" : "dev",
      "git" : {
         "git_clone_url" : "git@github.com:YordanGeorgiev/qto.git",
         "private_key_file" : "~/.ssh/id_rsa.ysg"
      },
      "db" : {
         "app_user_pwd" : "tf5V2AY0Tc7m",
         "postgres_db_user_pw" : "YHNTstuW3RrB",
         "postgres_db_user" : "usrqtoapp",
         "root_pwd" : "pTpbsOT57Gph",
         "postgres_db_host" : "127.0.0.1",
         "postgres_db_name" : "dev_qto",
         "postgres_db_useradmin" : "usrqtoadmin",
         "postgres_db_port" : "15432",
         "postgres_db_useradmin_pw" : "eWORG7Tmy2xX"
      },
      "aws" : {
         "key_name" : "id_rsa.ysg.pub",
         "secret_key" : "JsYX8f05NHfa",
         "access_key" : "0VRARhNeuZFn",
         "availability_zone" : "eu-west-1c",
         "public_key_path_comment" : "this one ^^^ has to be absolute file path",
         "aws_region" : "eu-west-1",
         "public_key_path" : "/home/ysg/.ssh/id_rsa.ysg.pub",
         "ssh_key_pair_file" : "~/.ssh/key-pair-qto-amzn.pem"
      }
   },
   "interpolation_comment" : "the declaration order matters, already declared vars are interpolated"
}
