{"1c753031-d29f-4ab1-b413-378238651c22":{"status":"09-done","guid":"1c753031-d29f-4ab1-b413-378238651c22","update_time":"2018-07-03 04:46:11","tags":" setup","stop_time":"2018-06-04 22:30:00","start_time":"2018-06-04 21:00:00","level":1,"seq":5,"weight":1,"category":"setup","description":"Root cause - simple return in the wrong way of the loop ","planned_hours":"0.00","id":1806011702,"name":"fix bug for non-aplying multiple with url params","type":"bug","owner":"ysg","actual_hours":"1.50","rows_count":85,"prio":9},"49f3bcbb-15b5-4ec4-bcf8-ed0c5c8af7ee":{"level":2,"seq":10,"description":"add the web list controller “\n - implementation code\n - tests \n - documentation additions for :\n-- requirements\n-- userstories\n-- tests \n-- features and functionalities","category":" feature","weight":5,"planned_hours":"3.00","id":1804020101,"guid":"49f3bcbb-15b5-4ec4-bcf8-ed0c5c8af7ee","status":"09-done","update_time":"2018-07-03 04:46:11","start_time":"2018-04-02 18:00:00","stop_time":"2018-05-02 18:00:00","tags":"feature","owner":"ysg","type":"feature","actual_hours":"0.10","rows_count":85,"prio":5,"name":"add the web list controller"},"dc8ce3c3-83e7-4bac-9aa7-1613cc8b2206":{"owner":"ysg","type":"feature-implementation","rows_count":85,"actual_hours":"0.10","prio":5,"name":"add export to txt from web ui","seq":10,"level":1,"description":"add export to txt from web ui","weight":5,"category":"feature","id":1805282138,"planned_hours":"4.00","guid":"dc8ce3c3-83e7-4bac-9aa7-1613cc8b2206","status":"02-todo","update_time":"2018-07-03 04:46:11","stop_time":"2018-12-30 00:00:00","start_time":"2018-01-01 00:00:00","tags":null},"5a9326d5-5358-4ff5-9ba4-0b416be9ba46":{"id":1805111300,"planned_hours":"0.10","description":"Create the create.pm action and integrate within the existing integration tests","weight":7,"category":" feature","seq":10,"level":1,"stop_time":"2018-06-30 07:00:00","start_time":"2018-05-30 07:00:00","tags":" feature","update_time":"2018-07-03 04:46:11","guid":"5a9326d5-5358-4ff5-9ba4-0b416be9ba46","status":"02-todo","prio":3,"actual_hours":"0.10","rows_count":85,"owner":"ysg","type":"activity","name":"add the create.pm web action"},"22b0dc7a-5897-415e-86c7-e3f3548364fd":{"type":"task","owner":"ysg","prio":5,"rows_count":85,"actual_hours":"1.00","name":"add pages minification on deployment","weight":7,"category":" feature","description":"Pages must be minified as 1/3 of the data is white space … ","seq":10,"level":1,"planned_hours":"20.00","id":1806281640,"update_time":"2018-07-03 04:46:11","status":"02-todo","guid":"22b0dc7a-5897-415e-86c7-e3f3548364fd","tags":"setup","stop_time":"2018-12-30 00:00:00","start_time":"2018-10-01 00:00:00"},"2d9c9ea5-e4bd-4f84-b319-ac440dbe8732":{"status":"09-done","guid":"2d9c9ea5-e4bd-4f84-b319-ac440dbe8732","update_time":"2018-07-03 04:46:11","tags":null,"stop_time":"2018-05-12 21:00:00","start_time":"2018-05-12 20:00:00","level":1,"seq":10,"category":" feature","weight":1,"description":"add the mysql db creation and population, add the documentation generation","id":1805082200,"planned_hours":"2.00","name":"improve integration testing","type":"feature","owner":"ysg","rows_count":85,"actual_hours":"2.00","prio":9},"b794b359-b4a4-427e-883e-67cea6fcef6d":{"guid":"b794b359-b4a4-427e-883e-67cea6fcef6d","status":"02-todo","update_time":"2018-07-03 04:46:11","stop_time":"2017-09-21 07:00:00","start_time":"2017-09-21 07:00:00","tags":"docs","seq":10,"level":1,"description":"The get controller will fetch a single item based on either on the id or the guid","category":" docs","weight":5,"planned_hours":"2.00","id":1805010100,"name":"add the Get.pm web app controller","owner":"ysg","type":"task","actual_hours":"10.10","rows_count":85,"prio":5},"c0c32b56-a3ac-439b-aba2-f5faab9a29ae":{"type":"task","owner":"ysg","rows_count":85,"actual_hours":"0.20","prio":6,"name":"add a modal dialog edit form for the edit action","level":1,"seq":10,"category":"feature","weight":7,"description":"Could be either from the list as html page or from the list as lables page","id":1806110034,"planned_hours":"30.00","status":"02-todo","guid":"c0c32b56-a3ac-439b-aba2-f5faab9a29ae","update_time":"2018-07-03 04:46:11","tags":null,"start_time":"2018-07-30 00:00:00","stop_time":"2018-08-31 00:00:00"},"a90bd18d-523c-4031-9fff-b814314e018f":{"name":"define REST API response structure","owner":"ysg","type":"specs","prio":9,"actual_hours":"2.00","rows_count":85,"update_time":"2018-07-03 04:46:11","status":"09-done","guid":"a90bd18d-523c-4031-9fff-b814314e018f","tags":null,"stop_time":"2018-05-30 00:00:00","start_time":"2018-05-10 20:53:00","category":"specs","weight":1,"description":"Should support messages and return codes as well as data transfer. \nDefined : \n - ret - containing the http status code\n - msg - the msg to be passed to the client\n - dat - the data to be passed to the client","seq":10,"level":1,"id":1804300100,"planned_hours":"1.00"},"88ee5aa9-21e0-4b1f-abc2-fa488c9c5337":{"name":"add Update Controller for accepting the edit REST calls","rows_count":85,"actual_hours":"1.00","prio":1,"type":"task","owner":"ysg","tags":"setup","start_time":"2018-07-01 00:00:00","stop_time":"2018-07-30 00:00:00","status":"02-todo","guid":"88ee5aa9-21e0-4b1f-abc2-fa488c9c5337","update_time":"2018-07-03 04:46:11","id":1806281842,"planned_hours":"30.00","seq":2,"level":2,"weight":9,"category":" feature","description":"The Update Controller return the code of whether of not the update has succeeded:\n"},"ad3a2135-af29-4498-9d33-0e586ccd9c0e":{"name":"implement a sortable list table ui","prio":5,"rows_count":85,"actual_hours":"3.00","owner":"ysg","type":"feature","tags":"feature","stop_time":"2018-12-31 07:00:00","start_time":"2018-06-08 21:30:00","update_time":"2018-07-03 04:46:11","status":"09-done","guid":"ad3a2135-af29-4498-9d33-0e586ccd9c0e","id":1806011257,"planned_hours":"20.00","category":"feature","weight":9,"description":"Should be able : \n- with alternative row backgrounds for odd and even\n- to choose the order of the colums as the pick \n- to choose which columns to hide\n- to list ANY db table\n- provide the same url params as in the list labels page to the back-end \n","level":1,"seq":5},"ae501d0b-d46f-44f4-9716-58dad5da6c6b":{"owner":"ysg","type":"feature-implementation","actual_hours":"0.10","rows_count":85,"prio":9,"name":"poc for data-load testing","level":1,"seq":10,"description":"Duplicated by it-1805172136\nBecause if you cannot get it right from the very beginning than you will get it never ever right. \nimplement a poc for data-load testing with single table load to postgres with start and stop times recording\nAdd as a non-blocking post update for start_time and stop_time","category":" feature","weight":1,"id":1805140900,"planned_hours":"0.10","guid":"ae501d0b-d46f-44f4-9716-58dad5da6c6b","status":"04-diss","update_time":"2018-07-03 04:46:11","start_time":"2018-05-25 20:53:00","stop_time":"2018-06-30 00:00:00","tags":null},"6e106235-caf7-4a38-bfc1-03b52ca5d425":{"prio":9,"rows_count":85,"actual_hours":"2.00","type":"capability","owner":"ysg","name":"achieve capability to export to pdf list-cloud and list-lbls pages via chrome UI","id":1806071735,"planned_hours":"1.00","weight":1,"category":"setup","description":"Could be done only via the Chrome UI","seq":5,"level":1,"tags":" setup","start_time":"2018-06-04 21:00:00","stop_time":"2018-06-04 22:30:00","update_time":"2018-07-03 04:46:11","status":"09-done","guid":"6e106235-caf7-4a38-bfc1-03b52ca5d425"},"f55799ee-8d17-427d-96a5-8e01a4d509b5":{"start_time":"2018-01-01 00:00:00","stop_time":"2018-12-30 00:00:00","tags":null,"guid":"f55799ee-8d17-427d-96a5-8e01a4d509b5","status":"04-diss","update_time":"2018-07-03 04:46:11","id":1805282137,"planned_hours":"4.00","seq":10,"level":1,"description":"add export to xls from web ui","weight":1,"category":" feature","name":"add export to xls from web ui","rows_count":85,"actual_hours":"0.10","prio":9,"owner":"ysg","type":"feature-implementation"},"eb9c47d9-2d11-448f-a014-91f82f4f0a51":{"prio":5,"actual_hours":"0.00","rows_count":85,"owner":"ysg","type":"bug","name":"add error handler for xls-to-db when postgres and db table does not exist ","id":1805112000,"planned_hours":"3.00","weight":5,"category":"feature","description":"Some kind of proper error msg\n","level":1,"seq":10,"tags":null,"start_time":"2018-05-11 21:10:00","stop_time":"2018-06-11 19:20:31","update_time":"2018-07-03 04:46:11","status":"09-done","guid":"eb9c47d9-2d11-448f-a014-91f82f4f0a51"},"596ce8d8-94b9-4acc-8a5a-78184eda8378":{"prio":4,"rows_count":85,"actual_hours":"0.10","owner":"ysg","type":"activity","name":"add the select-update form page","planned_hours":"0.10","id":1805111200,"category":" feature","weight":6,"description":"To test the update action and to start avoiding using the xls","seq":10,"level":1,"tags":" feature","stop_time":"2018-06-30 07:00:00","start_time":"2018-05-30 07:00:00","update_time":"2018-07-03 04:46:11","status":"02-todo","guid":"596ce8d8-94b9-4acc-8a5a-78184eda8378"},"2ec9b635-bc83-4d99-9072-619258fca7b1":{"name":"add the pick in url to select in db reader control flow for List.pm controller","prio":9,"actual_hours":"7.00","rows_count":85,"owner":"ysg","type":"feature-implementation-implementation","tags":null,"stop_time":"2018-06-30 00:00:00","start_time":"2018-05-02 10:35:00","update_time":"2018-07-03 04:46:11","status":"09-done","guid":"2ec9b635-bc83-4d99-9072-619258fca7b1","planned_hours":"5.00","id":1805040100,"weight":1,"category":" feature","description":"add the pick in url to select in db reader control flow","level":1,"seq":10},"233571ea-24e5-4fd7-84b6-b817f3089c60":{"prio":5,"rows_count":85,"actual_hours":"2.00","type":"bug","owner":"ysg","name":"create scalable css dir structure for screen and print ","id":1806071734,"planned_hours":"1.00","description":"This will enable the definition of printable css styles completely independent from the desktop print styles … \n- for now only print and screen are supported ... \n- probably a new level for mobile / tablets would be needed ... ","category":"setup","weight":5,"seq":5,"level":1,"stop_time":"2018-06-04 22:30:00","start_time":"2018-06-04 21:00:00","tags":"feature","update_time":"2018-07-03 04:46:11","guid":"233571ea-24e5-4fd7-84b6-b817f3089c60","status":"09-done"},"bd20ef3b-73ba-4bea-8c12-35b2ca68154a":{"status":"09-done","guid":"bd20ef3b-73ba-4bea-8c12-35b2ca68154a","update_time":"2018-07-03 04:46:11","tags":"feature","stop_time":"2018-06-29 11:00:00","start_time":"2018-06-26 10:00:00","level":1,"seq":5,"category":"feature","weight":5,"description":"Just move the directory structure of the css's one level bellow … ","id":1806302301,"planned_hours":"1.00","name":"add support for multiple css themes","type":"refactor","owner":"ysg","actual_hours":"0.20","rows_count":85,"prio":5},"d7db2658-cfb7-4601-853b-c26d5579d3ed":{"update_time":"2018-07-03 04:46:11","guid":"d7db2658-cfb7-4601-853b-c26d5579d3ed","status":"09-done","start_time":"2018-06-08 14:00:00","stop_time":"2018-06-08 16:00:00","tags":" setup","description":"Installed and documented the installation - this starts the solution of the crashing xls problem which is a blocker. ","category":"setup","weight":5,"seq":5,"level":1,"planned_hours":"0.00","id":1806062255,"name":"add the phppgadmin to the configurtion setup","owner":"ysg","type":"setup","prio":5,"actual_hours":"2.00","rows_count":85},"c209e3b9-f918-4747-a8cc-0ffa1eade7e2":{"owner":"ysg","type":"feature-implementation","prio":9,"rows_count":85,"actual_hours":"1.00","name":"change the id's naming convention to be to hour proximity and not day only ","description":"As the day seems to be too less ... As the id's must be copieable from one table to another and quickly collisions might be created. ","category":"specs","weight":1,"level":1,"seq":10,"planned_hours":"2.00","id":1805120100,"update_time":"2018-07-03 04:46:11","guid":"c209e3b9-f918-4747-a8cc-0ffa1eade7e2","status":"09-done","stop_time":"2018-05-30 20:53:00","start_time":"2018-05-10 20:53:00","tags":null},"d26df3ce-22a8-416e-a33b-a64339f5319f":{"name":"add modal dialog for item-edit in the list table ui","rows_count":85,"actual_hours":"2.00","prio":4,"type":"task","owner":"ysg","start_time":"2018-06-01 00:00:00","stop_time":"2018-07-30 00:00:00","tags":"feature","guid":"d26df3ce-22a8-416e-a33b-a64339f5319f","status":"01-eval","update_time":"2018-07-03 04:46:11","planned_hours":"50.00","id":1806232256,"level":1,"seq":10,"description":"add modal dialog for item-edit in the list table ui","weight":9,"category":" feature"},"fb0b0fd9-9ca0-4ec1-98c1-9c2fab4e7993":{"planned_hours":"2.00","id":1806011648,"seq":5,"level":1,"description":"setup nodejs, webpack and bower for Front-End development","weight":2,"category":"setup","start_time":"2018-06-01 00:00:00","stop_time":"2018-06-01 00:00:00","tags":" setup","guid":"fb0b0fd9-9ca0-4ec1-98c1-9c2fab4e7993","status":"09-done","update_time":"2018-07-03 04:46:11","actual_hours":"2.00","rows_count":85,"prio":8,"type":"setup","owner":"ysg","name":"Install FE required binaries"},"2174f5d1-8f60-4095-927f-e687079cb5ea":{"owner":"ysg","type":"feature-implementation-implementation","prio":9,"actual_hours":"0.25","rows_count":85,"name":"add the error halding for non-existent db in List.pm controller","description":"add the error halding for non-existent db in List.pm controller","weight":1,"category":" feature","level":1,"seq":10,"id":1805070100,"planned_hours":"0.10","update_time":"2018-07-03 04:46:11","guid":"2174f5d1-8f60-4095-927f-e687079cb5ea","status":"09-done","start_time":"2018-05-02 10:35:00","stop_time":"2018-06-30 00:00:01","tags":null},"880a44ca-e87f-4dac-8ba2-057f4bd204c7":{"name":"fix bug for increase-date","prio":5,"rows_count":85,"actual_hours":"2.00","owner":"ysg","type":"feature","start_time":"2018-06-28 20:53:00","stop_time":"2018-06-30 00:00:00","tags":"bug,feature-root-cause","update_time":"2018-07-03 04:46:11","guid":"880a44ca-e87f-4dac-8ba2-057f4bd204c7","status":"09-done","id":1806281041,"planned_hours":"1.00","description":"The increase date shell action now:\n - supports different sub-dirs - xls,json,txt","weight":9,"category":"testing","seq":5,"level":1},"5910b847-0491-4b8b-8db9-268ef97b6162":{"name":"improve the select-tables web action","owner":"ysg","type":"feature-implementation","prio":6,"rows_count":85,"actual_hours":"0.10","update_time":"2018-07-03 04:46:11","status":"01-eval","guid":"5910b847-0491-4b8b-8db9-268ef97b6162","tags":null,"stop_time":"2018-05-30 00:00:00","start_time":"2018-05-10 20:53:00","category":"feature","weight":1,"description":"Add the following:\n - list of views\n - order by table name\n - convert result-set to array and not hash","seq":10,"level":2,"id":1805110400,"planned_hours":"1.00"},"e2bca2fc-9c6a-40fa-8256-d7095f43a78a":{"tags":"feature,xls","start_time":"2018-07-01 00:00:00","stop_time":"2018-07-01 00:00:00","status":"02-todo","guid":"e2bca2fc-9c6a-40fa-8256-d7095f43a78a","update_time":"2018-07-03 04:46:11","id":1806251101,"planned_hours":"2.00","seq":10,"level":1,"category":"feature","weight":3,"description":"By running in sequence read xls , file, write to db for each table","name":"speed-up the xls-to-db action","rows_count":85,"actual_hours":"0.10","prio":6,"owner":"ysg","type":"task"},"7a28a769-8028-41a5-ab2f-489c7ad5dc42":{"weight":1,"category":"setup","description":"Need to implement own sorting method. \nThis is complete no-go for correct financial data !!!","level":1,"seq":5,"id":1806110038,"planned_hours":"5.00","update_time":"2018-07-03 04:46:11","status":"09-done","guid":"7a28a769-8028-41a5-ab2f-489c7ad5dc42","tags":" setup","start_time":"2018-06-10 21:30:00","stop_time":"2018-12-31 07:00:00","owner":"ysg","type":"bug","prio":7,"actual_hours":"0.30","rows_count":85,"name":"the client side ui sorter does not support soring by numbers"},"3a8a4d34-b234-4648-b449-2be9ffc7e349":{"planned_hours":"5.00","id":1805202317,"description":"Add include directive in the page:\n - ok for add layout page\n - todo for add the control css from the control to the layout","category":" feature","weight":1,"level":1,"seq":10,"start_time":"2018-05-16 21:10:00","stop_time":"2018-05-16 22:10:00","tags":null,"update_time":"2018-07-03 04:46:11","guid":"3a8a4d34-b234-4648-b449-2be9ffc7e349","status":"09-done","prio":9,"actual_hours":"3.00","rows_count":85,"owner":"ysg","type":"feature-implementation","name":"separate the control and the page code"},"dfde0a28-23a4-4195-bf15-15f6e49e184c":{"name":"add the filter-by url param for the list web control ","prio":9,"rows_count":85,"actual_hours":"2.00","owner":"ysg","type":"feature-implementation","tags":null,"stop_time":"2017-06-29 07:00:00","start_time":"2017-05-14 07:00:00","update_time":"2018-07-03 04:46:11","status":"09-done","guid":"dfde0a28-23a4-4195-bf15-15f6e49e184c","planned_hours":"5.00","id":1805161613,"weight":1,"category":" feature","description":"add the filter-by url param for the list web control\n - ok path\n - nok path ","seq":10,"level":2},"aabf0dc1-fa54-4395-9986-d048e5518e08":{"category":"activities","weight":5,"description":"add link to the git-hub","seq":10,"level":1,"id":1805110600,"planned_hours":"0.10","update_time":"2018-07-03 04:46:11","status":"02-todo","guid":"aabf0dc1-fa54-4395-9986-d048e5518e08","tags":null,"start_time":"2018-05-06 07:00:00","stop_time":"2018-12-31 07:00:00","owner":"ysg","type":"activity","prio":5,"actual_hours":"0.10","rows_count":85,"name":"publish a read-only issue-tracker MVP to a host in the cloud for demo purposes"},"1ac1c5d0-25ff-4477-b1e6-6bc0cbe3772b":{"name":"add the order-by url param for the list web control ","actual_hours":"2.00","rows_count":85,"prio":9,"owner":"ysg","type":"feature-implementation","start_time":"2018-05-14 07:00:00","stop_time":"2018-06-29 07:00:00","tags":null,"guid":"1ac1c5d0-25ff-4477-b1e6-6bc0cbe3772b","status":"09-done","update_time":"2018-07-03 04:46:11","id":1805152400,"planned_hours":"5.00","level":2,"seq":10,"description":"add the order-by url param for the list web control \n - ok path\n - nok path","category":" feature","weight":1},"3ac828f0-308b-4dff-8bb5-b8259bcd33fe":{"seq":10,"level":1,"description":"implement the copy by id via the back-end api from one table to another","category":"feature","weight":1,"planned_hours":"20.10","id":1707200100,"guid":"3ac828f0-308b-4dff-8bb5-b8259bcd33fe","status":"02-todo","update_time":"2018-07-03 04:46:11","stop_time":"2019-01-01 00:00:00","start_time":"2019-01-01 00:00:00","tags":null,"owner":"ysg","type":"task","rows_count":85,"actual_hours":"0.10","prio":9,"name":"implement the copy by id via the back-end api from one table to another"},"bddfedfa-b732-45fa-b30a-a94c0229e989":{"update_time":"2018-07-03 04:46:11","guid":"bddfedfa-b732-45fa-b30a-a94c0229e989","status":"09-done","stop_time":"2018-05-16 22:10:00","start_time":"2018-05-16 21:10:00","tags":null,"description":"add the with-col=val url param","category":"feature","weight":5,"level":1,"seq":10,"id":1805222246,"planned_hours":"4.00","name":"add the with-col=val url param","owner":"ysg","type":"feature-implementation","prio":5,"actual_hours":"6.00","rows_count":85},"2072325e-ad4b-423b-8c23-875b28dae2c5":{"id":1806232302,"planned_hours":"5.00","seq":10,"level":1,"category":" feature","weight":9,"description":"The CRUD functionality will require a generic forms creation","tags":"poc","stop_time":"2018-07-15 00:00:00","start_time":"2018-06-30 00:00:00","status":"02-todo","guid":"2072325e-ad4b-423b-8c23-875b28dae2c5","update_time":"2018-07-03 04:46:11","actual_hours":"0.30","rows_count":85,"prio":3,"owner":"ysg","type":"task","name":"evaluate a lib for the generic forms creation"},"2c49fad2-3d2e-4291-b2f5-409614d3452a":{"update_time":"2018-07-03 04:46:11","guid":"2c49fad2-3d2e-4291-b2f5-409614d3452a","status":"09-done","start_time":"2018-05-10 20:53:00","stop_time":"2018-05-30 00:00:01","tags":null,"description":"add the order-by in url to order by in db reader control flow in List.pm controller.\nChanged the format of the dat to array reference  because of the need to be able to pass a sorted data structure to the render json method. ","weight":1,"category":"feature","seq":10,"level":1,"id":1805060100,"planned_hours":"4.00","name":"add the order-by in url to order by in db reader control flow in List.pm controller","owner":"ysg","type":"feature-implementation","prio":9,"actual_hours":"3.00","rows_count":85},"4f6235f0-12a1-4927-a790-d56eedb4713b":{"owner":"ysg","type":"feature-implementation","rows_count":85,"actual_hours":"1.00","prio":5,"name":"add a default route for the \"/\" web address","level":1,"seq":10,"weight":5,"category":"feature","description":"add a default route for the \"/\" web address.\nMay be something like forward to the list view ?!","id":1805102300,"planned_hours":"2.00","status":"02-todo","guid":"4f6235f0-12a1-4927-a790-d56eedb4713b","update_time":"2018-07-03 04:46:11","tags":" feature,","start_time":"2018-05-10 20:53:00","stop_time":"2018-05-30 00:00:00"},"8c774ae0-7208-4060-842b-a05232789e3a":{"level":1,"seq":10,"weight":1,"category":" docs","description":"create the user manual document, which will contain ONLY business rules and logic as well as non-devops related content. ","planned_hours":"0.50","id":1805141000,"status":"04-diss","guid":"8c774ae0-7208-4060-842b-a05232789e3a","update_time":"2018-07-03 04:46:11","tags":null,"start_time":"2018-05-25 20:53:00","stop_time":"2018-05-30 00:00:00","owner":"ysg","type":"docs-addition","actual_hours":"0.50","rows_count":85,"prio":9,"name":"create user manual"},"e73e3f05-73d4-405c-b505-8c12deb354a1":{"id":1805110500,"planned_hours":"5.00","description":"add the like-by and like-val in url to implement the like operator for filtering","category":"feature","weight":1,"level":1,"seq":10,"start_time":"2018-05-10 20:53:00","stop_time":"2018-05-30 00:00:00","tags":null,"update_time":"2018-07-03 04:46:11","guid":"e73e3f05-73d4-405c-b505-8c12deb354a1","status":"09-done","prio":9,"actual_hours":"3.00","rows_count":85,"type":"feature-implementation","owner":"ysg","name":"add the like-by and like-val in url to implement the like operator for filtering"},"2630098e-94e0-4861-ab3a-debfe7ca44a8":{"id":1805172115,"planned_hours":"4.00","category":" feature","weight":1,"description":"Because if you cannot get it right from the very beginning than you will get it never ever right. \nimplement a poc for data-load testing with single table load to postgres with start and stop times recording\nAdd as a non-blocking post update for start_time and stop_time.\nHad to increase the whole OS and redo the setup install for the perl modules and the postgres because of this one ... ","level":1,"seq":10,"tags":null,"start_time":"2018-05-16 21:10:00","stop_time":"2018-05-16 22:10:00","update_time":"2018-07-03 04:46:11","status":"09-done","guid":"2630098e-94e0-4861-ab3a-debfe7ca44a8","prio":9,"rows_count":85,"actual_hours":"0.50","owner":"ysg","type":"feature-implementation","name":"poc for client site JavaScript testing"},"84a41176-28ea-4e46-8ccd-afbfbec27435":{"start_time":"2018-01-01 00:00:00","stop_time":"2018-12-30 00:00:00","tags":"feature","update_time":"2018-07-03 04:46:11","guid":"84a41176-28ea-4e46-8ccd-afbfbec27435","status":"04-diss","planned_hours":"3.00","id":1805221029,"description":"The ability to order the form elements from the url ... By using the pick order and not a separate fo= ... ","weight":6,"category":" feature","seq":10,"level":1,"name":"add form order in url params","prio":4,"rows_count":85,"actual_hours":"0.10","owner":"ysg","type":"feature"},"c6d65e37-23b3-439e-bf67-9a3ffcb0956d":{"owner":"ysg","type":"feature","rows_count":85,"actual_hours":"1.50","prio":5,"name":"add the \"like\" operator in the \"where\" url parameter","seq":5,"level":1,"category":"feature","weight":5,"description":"The like operator would select rows as follows:\n- where=<<column>>-<<operator>>-<<value>> , ","planned_hours":"0.10","id":1806011703,"status":"09-done","guid":"c6d65e37-23b3-439e-bf67-9a3ffcb0956d","update_time":"2018-07-03 04:46:11","tags":"feature","start_time":"2018-06-05 13:00:00","stop_time":"2018-06-05 14:00:00"},"8ffebc75-5048-4413-bfce-8c869c2215f9":{"level":2,"seq":10,"description":"add the hide url param for the list web control\n - ok path\n - nok path","weight":1,"category":" feature","id":1805152300,"planned_hours":"5.00","guid":"8ffebc75-5048-4413-bfce-8c869c2215f9","status":"09-done","update_time":"2018-07-03 04:46:11","start_time":"2018-05-14 07:00:00","stop_time":"2018-06-29 07:00:00","tags":null,"type":"feature-implementation","owner":"ysg","rows_count":85,"actual_hours":"2.00","prio":9,"name":"add the hide url param for the list web control"},"a5336b06-6cd4-47da-ab60-0ce2aba1806a":{"owner":"ysg","type":"task","actual_hours":"1.00","rows_count":85,"prio":1,"name":"add CRUD table control with dummy console.log calls","seq":2,"level":2,"description":"So that only the UI interface events will be captured … \n","weight":9,"category":" feature","planned_hours":"30.00","id":1806281841,"guid":"a5336b06-6cd4-47da-ab60-0ce2aba1806a","status":"02-todo","update_time":"2018-07-03 04:46:11","start_time":"2018-07-01 00:00:00","stop_time":"2018-07-30 00:00:00","tags":"setup"},"ec95c7e6-2b05-4548-8c0d-152bf2e42582":{"name":"add omnibox poc page with web service for projects search","prio":5,"rows_count":85,"actual_hours":"2.50","owner":"ysg","type":"poc-feature","tags":null,"stop_time":"2018-08-31 00:00:00","start_time":"2018-08-01 00:00:00","update_time":"2018-07-03 04:46:11","status":"04-diss","guid":"ec95c7e6-2b05-4548-8c0d-152bf2e42582","planned_hours":"3.00","id":1806081610,"category":"feature","weight":5,"description":"To be moved to the next month. \nadd omnibox poc page with web service for projects search. The end goal should be pop-up omnibox which will present the results on enter lepton like... ","level":1,"seq":10},"fcb35a01-90da-4117-a49c-61ba7e5f58b4":{"name":"add the hide, which should pick the columns' values but not display them in the result set","owner":"ysg","type":"feature-implementation","actual_hours":"7.00","rows_count":85,"prio":9,"guid":"fcb35a01-90da-4117-a49c-61ba7e5f58b4","status":"09-done","update_time":"2018-07-03 04:46:11","stop_time":"2018-05-30 00:00:00","start_time":"2018-05-10 20:53:00","tags":null,"level":1,"seq":10,"description":"add the hide, which should pick the columns' values but not display them in the result set","category":"feature","weight":1,"id":1805130100,"planned_hours":"4.00"},"afe9c830-2a96-4341-bb36-f24ad65704ea":{"planned_hours":"10.00","id":1805242250,"description":"Should increaese the ability to comprehend the issues. \nhttp://mistic100.github.io/jQCloud/demo.html\n - refactor to factory design pattern ... ","category":"feature","weight":7,"level":1,"seq":10,"start_time":"2018-06-01 00:00:00","stop_time":"2018-12-30 00:00:00","tags":null,"update_time":"2018-07-03 04:46:11","guid":"afe9c830-2a96-4341-bb36-f24ad65704ea","status":"07-qas","prio":5,"actual_hours":"8.00","rows_count":85,"owner":"ysg","type":"feature","name":"create a tag cloud page "},"de13ee13-7571-4f40-9df5-dc099d1c4288":{"stop_time":"2018-06-30 00:00:00","start_time":"2018-06-24 00:00:00","tags":"feature","update_time":"2018-07-03 04:46:11","guid":"de13ee13-7571-4f40-9df5-dc099d1c4288","status":"09-done","planned_hours":"3.00","id":1806241429,"description":"The modal dialog will be used for the CRUD functionality from the list table view and for the search … \nSeems too primitive - for example does not have the close by pressing escape","category":"feature","weight":5,"seq":1,"level":1,"name":"add poc for vue modal dialog page","prio":3,"rows_count":85,"actual_hours":"0.70","owner":"ysg","type":"task"},"45351f4f-e5f5-48d2-a119-a9bc05a0fc3d":{"planned_hours":"1.00","id":1806011258,"level":1,"seq":5,"description":"The column order is shuffling depending on whether or not one choses the pick or leaves the pick url param ... ","weight":5,"category":"bug","start_time":"2018-06-10 23:56:00","stop_time":"2018-06-20 00:00:00","tags":" bug","guid":"45351f4f-e5f5-48d2-a119-a9bc05a0fc3d","status":"09-done","update_time":"2018-07-03 04:46:11","actual_hours":"0.30","rows_count":85,"prio":5,"type":"bug","owner":"ysg","name":"fix bug with column orders"},"71a70ca3-5373-4678-a430-a59540f3ac3c":{"owner":"ysg","type":"feature","prio":5,"rows_count":85,"actual_hours":"0.10","name":"implement a time report web ui page","description":"The time report web ui page will :\n - fetch the daily,weekly,monthly and yearly hours\n - get the allocated hours per time period\n - calculate the registered actual hours to the went-by hours of the start of the period\n - calculate the diff between the actual and passed-by hours\n- accessible from the list/table-name/?as=table url\n- should be able t osort the data","weight":5,"category":" feature","level":1,"seq":10,"id":1806011256,"planned_hours":"20.00","update_time":"2018-07-03 04:46:11","guid":"71a70ca3-5373-4678-a430-a59540f3ac3c","status":"01-eval","start_time":"2018-12-01 00:00:00","stop_time":"2018-12-31 07:00:00","tags":null},"e7efb0ef-11fe-4363-be37-7bd30b2713c2":{"name":"create the list page with vue.js","rows_count":85,"actual_hours":"12.00","prio":9,"type":"feature","owner":"ysg","tags":null,"stop_time":"2018-12-31 07:00:00","start_time":"2018-05-10 20:53:00","status":"09-done","guid":"e7efb0ef-11fe-4363-be37-7bd30b2713c2","update_time":"2018-07-03 04:46:11","planned_hours":"10.00","id":1805110200,"seq":10,"level":1,"category":" feature","weight":1,"description":"Create a simple list labels view interface which will use the list web action: \n - evaluate both server and client side html generation and compare performance\n- ok add error handling for missing db\n - add error handling for missing table\n- add error handling for wrong hidable column\n - add error handling for wrong pickable column\n - add error handling for wrong filterable col\n - add error handling for wrong col in like"},"d90fedcd-1191-4afa-9a87-8c289e706b1e":{"rows_count":85,"actual_hours":"1.00","prio":9,"owner":"ysg","type":"bug","name":"fix bug with non-publishing to google sheets ","id":1805102000,"planned_hours":"0.00","level":1,"seq":10,"description":"Due to the non-complience of the googleSheets controller with the Input-Output-Controller-Model architecture","weight":1,"category":" bugs","stop_time":"2018-05-30 09:54:00","start_time":"2018-05-10 20:53:00","tags":null,"guid":"d90fedcd-1191-4afa-9a87-8c289e706b1e","status":"09-done","update_time":"2018-07-03 04:46:11"},"60b0a558-fc50-404f-9976-18fca7f1a1c5":{"tags":"security","stop_time":"2018-12-31 07:00:00","start_time":"2018-06-10 23:00:00","status":"03-act","guid":"60b0a558-fc50-404f-9976-18fca7f1a1c5","update_time":"2018-07-03 04:46:11","id":1806110020,"planned_hours":"50.00","seq":10,"level":1,"weight":6,"category":" security","description":"Each time a new data param is to be parametrized till the db ... A validation must be added to it. ","name":"add validation of ui params against SQL injections","rows_count":85,"actual_hours":"3.00","prio":3,"owner":"ysg","type":"activity"},"791f9195-b57b-4039-a37d-ee0a1115cb88":{"tags":" feature","start_time":"2018-05-30 07:00:00","stop_time":"2018-06-30 07:00:00","status":"02-todo","guid":"791f9195-b57b-4039-a37d-ee0a1115cb88","update_time":"2018-07-03 04:46:11","id":1805111100,"planned_hours":"0.10","level":1,"seq":10,"category":" feature","weight":7,"description":"Create the update.pm action and integrate within the existing integration tests","name":"add the edit web action from the list as labels page","rows_count":85,"actual_hours":"0.10","prio":3,"owner":"ysg","type":"activity"},"5521c53f-dc3b-44e0-b3d3-e01988c91530":{"id":1805111000,"planned_hours":"2.00","weight":1,"category":"setup","description":"the run-integration tests should pre-load the configuration file of the current instance in order to match the full environment as it is run usually. \nSolution : \nThe call has to be changed to : \nexport issue_tracker_project=\"\"; bash src/bash/issue-tracker/issue-tracker.sh -a run-integration-tests\nAnd documented the change in the DevOps guide","seq":10,"level":1,"tags":null,"start_time":"2018-05-10 20:53:00","stop_time":"2018-05-31 17:00:00","update_time":"2018-07-03 04:46:11","status":"09-done","guid":"5521c53f-dc3b-44e0-b3d3-e01988c91530","prio":9,"actual_hours":"2.00","rows_count":85,"owner":"ysg","type":"feature-implementation","name":"add the pre-loading of the env shell configuration files"},"7395d8b2-e74d-4172-9def-ba020d1c66d4":{"name":"add the like-by url param for the list web control ","prio":9,"rows_count":85,"actual_hours":"2.00","owner":"ysg","type":"feature-implementation","stop_time":"2017-06-29 07:00:00","start_time":"2017-05-14 07:00:00","tags":null,"update_time":"2018-07-03 04:46:11","guid":"7395d8b2-e74d-4172-9def-ba020d1c66d4","status":"09-done","id":1805161614,"planned_hours":"5.00","description":"add the like-by url param for the list web control \n - ok path\n - nok path","weight":1,"category":" feature","level":2,"seq":10},"652330e5-058a-450e-b6f3-37fc62cb464d":{"name":"implement data load testing","owner":"ysg","type":"goal","prio":2,"rows_count":85,"actual_hours":"2.00","update_time":"2018-07-03 04:46:11","guid":"652330e5-058a-450e-b6f3-37fc62cb464d","status":"02-todo","stop_time":"2018-07-30 00:00:00","start_time":"2018-06-01 00:00:00","tags":"feature","description":"Should be single liner:\n - very simple\n - should have reliable start _time and stop_times\n - should be able to verify the executions times per request , request phases to keep track on performance while increasing complexity\n- and optionally all this by single user ","category":" feature","weight":9,"seq":10,"level":1,"id":1805172131,"planned_hours":"50.00"},"830a3d1a-1a31-48d5-bcc3-3aa3966a0c03":{"weight":1,"category":" feature","description":"add the pick url param for the list web control","level":2,"seq":10,"planned_hours":"5.00","id":1805152200,"update_time":"2018-07-03 04:46:11","status":"09-done","guid":"830a3d1a-1a31-48d5-bcc3-3aa3966a0c03","tags":null,"stop_time":"2018-06-29 07:00:00","start_time":"2018-05-14 07:00:00","owner":"ysg","type":"feature-implementation","prio":9,"actual_hours":"2.00","rows_count":85,"name":"add the pick url param for the list web control"},"4e7c25df-4f40-4d48-98a5-761e8d94eb1c":{"name":"add the feature for the validation of the spent time","actual_hours":"0.10","rows_count":85,"prio":5,"type":"task","owner":"ysg","stop_time":"2017-08-07 00:00:00","start_time":"2017-08-06 00:00:00","tags":null,"guid":"4e7c25df-4f40-4d48-98a5-761e8d94eb1c","status":"02-todo","update_time":"2018-07-03 04:46:11","planned_hours":"15.00","id":1805160700,"seq":10,"level":2,"description":"design the validation of the available time and the spent time = registered time","category":"feature","weight":5},"c1d792ad-635e-4140-b1ca-424994261b6b":{"status":"09-done","guid":"c1d792ad-635e-4140-b1ca-424994261b6b","update_time":"2018-07-03 04:46:11","tags":null,"start_time":"2018-04-02 18:00:00","stop_time":"2018-05-30 22:00:00","seq":10,"level":1,"weight":1,"category":"feature","description":"add the web select controller “\n - implementation code\n - tests \n - documentation additions for :\n-- requirements\n-- userstories\n-- tests \n-- features and functionalities","planned_hours":"3.00","id":1804020100,"name":"add the web select controller","type":"feature","owner":"ysg","actual_hours":"7.00","rows_count":85,"prio":9},"d0bd6574-93b5-488d-8078-d3b008f1b7c7":{"name":"add the list vue.js poc","actual_hours":"3.00","rows_count":85,"prio":9,"owner":"ysg","type":"task","tags":null,"stop_time":"2018-05-07 13:38:01","start_time":"2018-05-07 13:38:00","status":"09-done","guid":"d0bd6574-93b5-488d-8078-d3b008f1b7c7","update_time":"2018-07-03 04:46:11","planned_hours":"2.00","id":1805071500,"seq":10,"level":1,"category":" feature","weight":1,"description":"Create a proof of concept poc page with REST api fetch from the back-end using vue.js and axiom"},"9ad52d11-60da-4c68-b69f-e77f0ee1eb68":{"name":"aim to use the issue tracker more on the web interface and less on the xls ","actual_hours":"0.10","rows_count":85,"prio":5,"owner":"ysg","type":"activity","tags":null,"stop_time":"2018-12-31 07:00:00","start_time":"2018-05-06 07:00:00","status":"03-act","guid":"9ad52d11-60da-4c68-b69f-e77f0ee1eb68","update_time":"2018-07-03 04:46:11","id":1805110300,"planned_hours":"0.10","level":1,"seq":10,"weight":5,"category":"activities","description":"In order to increase the dog food experience and provide base for the creation of issues , userstories , requirements and other specifications "},"1b79ebbe-38c7-473f-b4e7-abc8f1b1552f":{"type":"feature","owner":"ysg","actual_hours":"8.00","rows_count":85,"prio":9,"name":"refactor list web action to support multiple output types","seq":6,"level":1,"weight":1,"category":"feature","description":"From now on the syntax for list?as=<<output-type>> would support multiple page builders for multiple output types.\nThe same approach could be provided to the following future web actions:\n - view , \n - edit , \n - create\n - search","id":1806061109,"planned_hours":"2.00","status":"09-done","guid":"1b79ebbe-38c7-473f-b4e7-abc8f1b1552f","update_time":"2018-07-03 04:46:11","tags":"feature ","stop_time":"2018-06-06 11:30:00","start_time":"2018-06-06 09:30:00"},"4a2ac474-935a-4d84-9146-81898ef76a13":{"rows_count":85,"actual_hours":"1.00","prio":9,"owner":"ysg","type":"bug","name":"fix bug with non-informance of missing db table on xls-to-db","id":1805312157,"planned_hours":"1.00","seq":10,"level":1,"weight":1,"category":" bugs","description":"when the xls sheet exists but the table not now the app quites","tags":null,"stop_time":"2018-05-30 09:54:00","start_time":"2018-05-10 20:53:00","status":"09-done","guid":"4a2ac474-935a-4d84-9146-81898ef76a13","update_time":"2018-07-03 04:46:11"},"4ed0d39c-1ad3-4ef4-b1f9-44d07b2d1697":{"update_time":"2018-07-03 04:46:11","status":"02-todo","guid":"4ed0d39c-1ad3-4ef4-b1f9-44d07b2d1697","tags":null,"stop_time":"2018-12-30 00:00:00","start_time":"2018-05-17 00:00:00","category":"deployment","weight":5,"description":"Deploy an instance of the issue-tracker application, which will be www readable, but editable via a simple authentication. ","level":1,"seq":10,"id":1805172136,"planned_hours":"20.10","name":"deploy a web accessible instance with basic authentication for demo purposes in amzn","owner":"ysg","type":"goal","prio":5,"rows_count":85,"actual_hours":"0.10"},"71f9f65d-5713-4916-a4e8-fb1a108f3f2e":{"prio":9,"actual_hours":"6.00","rows_count":85,"owner":"ysg","type":"feature-implementation-implementation","name":"add the filter-by in url to where in db reader control flow for List.pm controller","id":1805050102,"planned_hours":"7.00","weight":1,"category":" feature","description":"add the filter-by in url to where in db reader control flow for List.pm controller: \n - ok for ok case\n - add nok for col does not exist","level":1,"seq":10,"tags":null,"stop_time":"2018-06-30 00:00:00","start_time":"2018-05-02 10:35:53","update_time":"2018-07-03 04:46:11","status":"09-done","guid":"71f9f65d-5713-4916-a4e8-fb1a108f3f2e"},"4b20e738-2e1b-4154-bea5-de3b3db1be78":{"name":"create the select-create form page","rows_count":85,"actual_hours":"0.10","prio":4,"owner":"ysg","type":"activity","tags":" feature","start_time":"2018-05-30 07:00:00","stop_time":"2018-06-30 07:00:00","status":"02-todo","guid":"4b20e738-2e1b-4154-bea5-de3b3db1be78","update_time":"2018-07-03 04:46:11","planned_hours":"0.10","id":1805111400,"level":1,"seq":10,"weight":6,"category":" feature","description":"To test the create action and to start avoiding using the xls"},"ebd90ebe-a6d4-4f23-aae4-931469578ccf":{"tags":"setup","stop_time":"2018-07-30 00:00:00","start_time":"2018-07-01 00:00:00","update_time":"2018-07-03 04:46:11","status":"02-todo","guid":"ebd90ebe-a6d4-4f23-aae4-931469578ccf","id":1806281840,"planned_hours":"100.00","category":" feature","weight":9,"description":"Add CRUD table","level":1,"seq":1,"name":"add CRUD table","prio":1,"rows_count":85,"actual_hours":"1.00","owner":"ysg","type":"task"},"104ba339-b6b0-4bdd-88a4-b1c03bd50f76":{"prio":5,"rows_count":85,"actual_hours":"0.10","owner":"ysg","type":"task","name":"change Front-End architecture to use Web Pack","planned_hours":"50.00","id":1806011111,"description":"As Web Pack seems to be the best in town package manager and a lot of JS code is distributed as npm packages. ","weight":9,"category":" architure","seq":10,"level":1,"stop_time":"2018-07-30 00:00:00","start_time":"2018-06-01 00:00:00","tags":null,"update_time":"2018-07-03 04:46:11","guid":"104ba339-b6b0-4bdd-88a4-b1c03bd50f76","status":"03-wip"},"09c2f556-be83-4e13-b2e8-1677bdebeb3a":{"tags":"docs","stop_time":"2018-04-29 13:21:23","start_time":"2018-04-29 10:21:23","status":"09-done","guid":"09c2f556-be83-4e13-b2e8-1677bdebeb3a","update_time":"2018-07-03 04:46:11","planned_hours":"2.00","id":1804290100,"seq":10,"level":1,"weight":5,"category":" docs","description":"Or add the ability to resolve the dir structure of any perl script using the Initiator - obs has to be called only once ... \nfix nasty bug in Initiator cause by related dir in mojo testing framework.\nThe root cause - the Initiator used $0 while it should have used __FILE__. See :\nhttps://stackoverflow.com/a/90721/65706","name":"fix nasty bug in Initiator cause by related dir in mojo testing framework","rows_count":85,"actual_hours":"3.00","prio":5,"owner":"ysg","type":"task"},"4f75de1d-54db-41bf-9299-0cdaf93532ec":{"planned_hours":"0.10","id":1805172116,"description":"Upgrade zesty to artful:\n - had to pre-install the whole perl modules package bundle\n - had to pre-install postgres ... Althought it would have worked probably by just installing the Perl postgres related modules. ","weight":1,"category":" setup","seq":10,"level":1,"stop_time":"2018-05-20 23:10:00","start_time":"2018-05-20 19:10:00","tags":null,"update_time":"2018-07-03 04:46:11","guid":"4f75de1d-54db-41bf-9299-0cdaf93532ec","status":"09-done","prio":9,"actual_hours":"2.00","rows_count":85,"owner":"ysg","type":"feature-implementation","name":"upgrade Ubuntu 17.04->17.10"},"f88aba50-aac5-450a-bf7e-a296075ee6f4":{"prio":9,"rows_count":85,"actual_hours":"1.00","type":"bug","owner":"ysg","name":"poc for print-to-pdf via headless chrome","planned_hours":"3.00","id":1806062253,"description":"Could be achieved via UI , not so often used - no sence to spend time automating it … at least for now … ","category":"setup","weight":1,"seq":10,"level":1,"stop_time":"2018-06-04 22:30:00","start_time":"2018-06-04 21:00:00","tags":null,"update_time":"2018-07-03 04:46:11","guid":"f88aba50-aac5-450a-bf7e-a296075ee6f4","status":"04-diss"},"10a53d0d-bd49-43e6-8bd9-74e7161c76c4":{"update_time":"2018-07-03 04:46:11","guid":"10a53d0d-bd49-43e6-8bd9-74e7161c76c4","status":"09-done","start_time":"2017-09-21 07:00:00","stop_time":"2017-09-21 07:00:00","tags":"docs","description":"And move it to the System Guide , which seems to be a more logical place\nAdd it to the devops guide","weight":6,"category":" docs","level":1,"seq":10,"planned_hours":"2.00","id":1804260100,"name":"add the issue-tracker control flow diagram to the DevOps guide","owner":"ysg","type":"task","prio":4,"rows_count":85,"actual_hours":"0.10"},"fe05c624-5cf3-46dc-b19f-da2ac38aaa22":{"guid":"fe05c624-5cf3-46dc-b19f-da2ac38aaa22","status":"09-done","update_time":"2018-07-03 04:46:11","start_time":"2018-05-02 10:35:00","stop_time":"2018-06-30 00:00:00","tags":null,"level":1,"seq":10,"description":"add the filter-by in url to where in db reader control flow for List.pm controller: \n - ok for ok case\n - add nok for col does not exist","category":" feature","weight":1,"id":1805050100,"planned_hours":"7.00","name":"add the filter-by in url to where in db reader control flow for List.pm controller","owner":"ysg","type":"feature-implementation-implementation","actual_hours":"6.00","rows_count":85,"prio":9},"92076ba4-d303-4318-8bec-783b9be4b8ed":{"update_time":"2018-07-03 04:46:11","guid":"92076ba4-d303-4318-8bec-783b9be4b8ed","status":"02-todo","stop_time":"2018-12-31 07:00:00","start_time":"2018-05-12 20:00:00","tags":null,"description":"Create a simple list labels view interface which will use the list web action: \n - evaluete both server and client side html generation and compare performance","weight":4,"category":" feature","seq":10,"level":2,"planned_hours":"0.10","id":1805091300,"name":"create the view doc ui with vue.js","owner":"ysg","type":"feature","prio":6,"actual_hours":"0.10","rows_count":85},"d58684f2-8749-41c5-ab0c-aa74651fbc9c":{"type":"bug","owner":"ysg","prio":6,"actual_hours":"3.00","rows_count":85,"name":"fix the NULL.md generated in generate-docs action","category":"bug","weight":4,"description":"Due to the non availability of the relative path","level":1,"seq":10,"id":1805301337,"planned_hours":"2.00","update_time":"2018-07-03 04:46:11","status":"09-done","guid":"d58684f2-8749-41c5-ab0c-aa74651fbc9c","tags":null,"stop_time":"2018-05-30 00:00:00","start_time":"2018-05-28 20:53:00"},"b4286bc6-1951-4993-bfa9-08ece4a1d1d5":{"prio":5,"rows_count":85,"actual_hours":"0.10","type":"feature-implementation","owner":"ysg","name":"add db-to-json export for all the issues tables in the integration tests ","id":1805110401,"planned_hours":"4.00","weight":5,"category":"feature","description":"To enable later the avoidance of the xls file ... ","level":1,"seq":10,"tags":null,"start_time":"2018-05-10 20:53:00","stop_time":"2018-05-30 00:00:00","update_time":"2018-07-03 04:46:11","status":"04-diss","guid":"b4286bc6-1951-4993-bfa9-08ece4a1d1d5"},"b2b097e2-cea0-4fdd-a2c3-338bda470d1b":{"planned_hours":"50.00","id":1805172135,"level":1,"seq":10,"description":"By using the Mojo::Chrome module:\nShould be able to capture JS events:\nVue induced changes on the page. ","category":" feature","weight":9,"stop_time":"2018-07-30 00:00:00","start_time":"2018-06-01 00:00:00","tags":"feature","guid":"b2b097e2-cea0-4fdd-a2c3-338bda470d1b","status":"02-todo","update_time":"2018-07-03 04:46:11","actual_hours":"5.00","rows_count":85,"prio":2,"owner":"ysg","type":"goal","name":"implement client-side testing"},"ffe85c20-84bc-4898-be9c-d2dc7e0172fe":{"status":"02-todo","guid":"ffe85c20-84bc-4898-be9c-d2dc7e0172fe","update_time":"2018-07-03 04:46:11","tags":null,"start_time":"2018-10-01 00:00:00","stop_time":"2018-12-31 00:00:00","level":1,"seq":10,"weight":3,"category":"documentation","description":"Add an official component diagram UML-wise:\nhttp://agilemodeling.com/artifacts/componentDiagram.htm","id":1806251545,"planned_hours":"3.00","name":"add a component diagram","owner":"ysg","type":"task","actual_hours":"0.10","rows_count":85,"prio":9},"666aa682-8532-41cf-8d71-971ad0090c5a":{"update_time":"2018-07-03 04:46:11","status":"09-done","guid":"666aa682-8532-41cf-8d71-971ad0090c5a","tags":"bugs","start_time":"2018-05-30 20:53:00","stop_time":"2018-06-09 10:00:00","weight":5,"category":"issue-tracker","description":"Due to false logic in the implementation","seq":4,"level":1,"id":1806091100,"planned_hours":"1.00","name":"fix bug for non-arranging the column in the list labels as specified in the pick order","type":"bug","owner":"ysg","prio":5,"actual_hours":"0.20","rows_count":85},"7159a37f-d279-4ffb-8ee9-7c5224c1f277":{"actual_hours":"0.10","rows_count":85,"prio":5,"owner":"ysg","type":"feature","name":"create the plain list labels view ui  with vue.js","id":1805110201,"planned_hours":"0.10","seq":10,"level":1,"category":"feature","weight":5,"description":"Create a simple list labels view interface which will use the list web action: \n - evaluete both server and client side html generation and compare performance","tags":"feature","stop_time":"2018-12-31 07:00:00","start_time":"2018-05-10 20:53:00","status":"09-done","guid":"7159a37f-d279-4ffb-8ee9-7c5224c1f277","update_time":"2018-07-03 04:46:11"},"51dc889c-0731-4f05-9252-70ef30371374":{"update_time":"2018-07-03 04:46:11","status":"09-done","guid":"51dc889c-0731-4f05-9252-70ef30371374","tags":"feature","stop_time":"2018-06-30 00:00:00","start_time":"2018-06-23 00:00:00","category":" feature","weight":9,"description":"In order to achieve independance from the xls run-time for achieving the full CRUD, I wanto to be able to take quickly backup and restore db data from files on timely basis. ","level":1,"seq":10,"planned_hours":"2.00","id":1806232301,"name":"add json-to-db shell action","owner":"ysg","type":"task","prio":1,"rows_count":85,"actual_hours":"0.10"},"a579f539-e308-4a8e-bbbb-daf35086127f":{"level":1,"seq":10,"description":"Add server side paging with callable page size , and page number:\n - limit\n - ","weight":6,"category":" feature","id":1806092324,"planned_hours":"20.00","guid":"a579f539-e308-4a8e-bbbb-daf35086127f","status":"09-done","update_time":"2018-07-03 04:46:11","stop_time":"2018-10-30 00:00:00","start_time":"2018-06-30 00:00:00","tags":" architecture","owner":"ysg","type":"task","actual_hours":"0.10","rows_count":85,"prio":4,"name":"add server side paging"},"13c5c132-ff82-456e-9b1d-a3168f55f7e4":{"description":"add the where url operator for quick sql liker filtering","category":" feature","weight":1,"level":2,"seq":10,"id":1805160800,"planned_hours":"15.00","update_time":"2018-07-03 04:46:11","guid":"13c5c132-ff82-456e-9b1d-a3168f55f7e4","status":"09-done","start_time":"2017-08-06 00:00:00","stop_time":"2017-08-07 00:00:00","tags":null,"type":"task","owner":"ysg","prio":9,"actual_hours":"0.10","rows_count":85,"name":"add the where url operator for quick sql liker filtering"},"b711d2f7-3889-4766-8526-00b64159427d":{"update_time":"2018-07-03 04:46:11","guid":"b711d2f7-3889-4766-8526-00b64159427d","status":"06-onhold","start_time":"2018-07-10 00:00:00","stop_time":"2018-08-30 00:00:00","tags":"setup","description":"When the ui scrolls a table with page containing more items than the height of the screen the headers of the table must stick to the top of the page. \nQuite difficult with pure css … this one has been the best so far : \nhttps://jsfiddle.net/dPixie/byB9d/3/","weight":6,"category":" feature","level":1,"seq":1,"planned_hours":"3.00","id":1806291840,"name":"add columns stickiness in list as table ui","type":"task","owner":"ysg","prio":3,"rows_count":85,"actual_hours":"1.50"}}