{"5d1a1292-044f-4aeb-8b92-4dc3f00175c4":{"actual_hours":"0.10","rows_count":6,"category":"issue-tracker,ui","description":"would require a totally new approach to ui design + possibly changes to the css dir structure","status":"03-act","level":1,"planned_hours":"100.00","stop_time":"2020-01-01","tags":null,"prio":5,"start_time":"2019-01-01","update_time":"2018-06-23 23:55:38.190714","weight":5,"name":"add support for visual themes ","guid":"5d1a1292-044f-4aeb-8b92-4dc3f00175c4","id":1806110013,"type":"milestone","owner":"ysg","seq":null},"f685fb8e-141c-4a2d-a062-5cdfbc994c00":{"status":"03-act","description":"complete secured instance in the web:\n - OAuth2 , authorization and authentication \n - full CRUD ui for issues,projects,problems,questions,principles\n - history data management\n - time tracking biz features","rows_count":6,"category":"issue-tracker","actual_hours":"0.10","prio":5,"tags":null,"planned_hours":"450.00","stop_time":"2019-06-30","level":1,"weight":5,"update_time":"2018-06-23 23:55:38.190714","start_time":"2019-01-01","seq":null,"owner":"ysg","type":"goal","guid":"f685fb8e-141c-4a2d-a062-5cdfbc994c00","id":1806011301,"name":"complete secured instance in the web"},"076307a9-6efc-4255-af6a-59186f31829b":{"status":"03-act","description":"aquire more than 20 users to feed in data of issue-tracker prjojects","rows_count":6,"category":"issue-tracker","actual_hours":"3.00","prio":5,"tags":null,"planned_hours":"200.00","level":1,"stop_time":"2019-01-01","weight":5,"start_time":"2018-06-01","update_time":"2018-06-23 23:55:38.190714","seq":null,"owner":"ysg","type":"goal","id":1806011305,"guid":"076307a9-6efc-4255-af6a-59186f31829b","name":"20 users for issue-tracker projects"},"43106eaf-c3da-4257-8b2b-3d3d6495da6d":{"name":"attract 2 full stack developers for collaboration","id":1806011304,"guid":"43106eaf-c3da-4257-8b2b-3d3d6495da6d","type":"goal","owner":"ysg","seq":null,"update_time":"2018-06-23 23:55:38.190714","start_time":"2018-05-08","weight":5,"planned_hours":"30.00","level":1,"stop_time":"2020-01-01","tags":null,"prio":5,"actual_hours":"2.00","category":"issue-tracker","rows_count":6,"description":"attract 2 full stack developers for collaboration","status":"03-act"},"3edff973-7233-4c3a-8396-da0105e0bcdb":{"actual_hours":"0.10","category":"issue-tracker","rows_count":6,"description":"Deploy to an amzn instance :\n - minimalistic mvp with gruds and basic ui\n - basic auth\n - multiple projects","status":"03-act","planned_hours":"450.00","stop_time":"2019-01-01","level":1,"tags":null,"prio":5,"update_time":"2018-06-23 23:55:38.190714","start_time":"2018-06-01","weight":5,"name":"minimalistic MVP with basic auth in the web","id":1806011302,"guid":"3edff973-7233-4c3a-8396-da0105e0bcdb","type":"goal","seq":null,"owner":"ysg"},"650d520b-be3d-4aa4-99da-af9112e1c832":{"name":"get 10 starts and 5 pull requests","id":1806011303,"guid":"650d520b-be3d-4aa4-99da-af9112e1c832","type":"goal","owner":"ysg","seq":null,"start_time":"2018-06-01","update_time":"2018-06-23 23:55:38.190714","weight":5,"planned_hours":"30.00","stop_time":"2019-01-01","level":1,"tags":null,"prio":5,"actual_hours":"2.00","category":"issue-tracker","rows_count":6,"description":"By achieving 10 stars and 5 pull requests","status":"03-act"}}